doc/__init__.py
doc/conf.py
joblibspark/__init__.py
joblibspark/backend.py
joblibspark/utils.py
joblibspark-0.6.0.dist-info/licenses/LICENSE
test/__init__.py
test/test_backend.py
test/test_spark.py
joblibspark-0.6.0.dist-info/METADATA
joblibspark-0.6.0.dist-info/WHEEL
joblibspark-0.6.0.dist-info/top_level.txt
joblibspark-0.6.0.dist-info/RECORD
